{
  "Math": {
    "Quarter 1": [
      "Angles (Right, Acute, Obtuse)",
      "Measuring Angles with a Protractor",
      "Triangles and Quadrilaterals",
      "Classifying Triangles and Quadrilaterals",
      "Perimeter of Quadrilaterals",
      "Perimeter of Composite Figures",
      "Reading and Writing Numbers up to 1 000 000",
      "Place Value of 6-Digit Numbers",
      "Comparing Numbers using =, <, >",
      "Rounding to the Nearest Hundred Thousand",
      "Estimating Sums and Differences",
      "Addition and Subtraction up to 1 000 000"
    ],
    "Quarter 2": [
      "Multiplication with Products up to 1 000 000",
      "Estimating Products",
      "Division of 3- to 4-Digit Numbers",
      "Estimating Quotients",
      "MDAS Rules",
      "Multi-Step Word Problems (Including Money)",
      "Converting Units of Length, Mass, and Capacity",
      "Converting Units of Time",
      "Elapsed Time Problems",
      "Similar Fractions (Proper, Improper, Mixed)",
      "Adding and Subtracting Similar Fractions"
    ],
    "Quarter 3": [
      "Dissimilar Fractions",
      "Comparing and Ordering Dissimilar Fractions",
      "Equivalent Fractions",
      "Factors and Multiples up to 100",
      "Reducing Fractions to Simplest Form",
      "Adding and Subtracting Dissimilar Fractions",
      "Multi-Step Fraction Problems",
      "Line Symmetry",
      "Reflection of Figures"
    ],
    "Quarter 4": [
      "Collecting and Presenting Data in Tables",
      "Single Line Graphs",
      "Interpreting Data",
      "Simple Patterns",
      "Number Sentences",
      "Decimal Numbers and Fractions",
      "Place Value of Decimals to Hundredths",
      "Comparing and Ordering Decimals",
      "Rounding Decimals"
    ]
  },
  "Science": {
    "Quarter 1": [
      "Science Inventions and Filipino Scientists",
      "Science Inventions in Everyday Life",
      "Chemical Properties of Materials",
      "Changes in Materials Due to Temperature",
      "Minimizing Harmful Changes in Materials",
      "Science and Community Environmental Issues",
      "Gathering Scientific Information"
    ],
    "Quarter 2": [
      "Human Body Systems",
      "Root and Shoot Systems of Plants",
      "Philippine Animals and Their Habitats",
      "Animals and Plants in Local Habitats",
      "Life Cycles of Animals",
      "Herbivores, Carnivores, and Omnivores",
      "Food Chains"
    ],
    "Quarter 3": [
      "Forces and Movement",
      "Measuring Distance and Time",
      "Speed",
      "Pushes and Pulls",
      "How Forces Change the Shape of Objects",
      "Properties of Magnets",
      "Light, Sound, and Heat Energy",
      "Sources and Uses of Energy"
    ],
    "Quarter 4": [
      "Types of Soil",
      "Soil and Plant Growth",
      "Water as a Basic Need",
      "Characteristics of Weather",
      "Weather Instruments",
      "Weather Charts and Safety",
      "The Sun",
      "Shadows and the Sun's Position"
    ]
  },
  "Araling Panlipunan": {
    "Quarter 1": [
      "Ang Heograpiya ng Pilipinas",
      "Paggamit ng Mapa at Globo",
      "Tiyak (Absolute) na Lokasyon",
      "Relatibong Lokasyon",
      "Ang Pambansang Teritoryo",
      "Saligan ng Teritoryo",
      "Teritoryo Ayon sa Kasaysayan",
      "Teritoryo Ayon sa Saligang Batas",
      "Teritoryo Ayon sa Atas ng Pangulo",
      "Doktrinang Pangkapuluan (Archipelagic Doctrine-UNCLOS)",
      "Pagkakakilanlang Heograpikal",
      "Heograpiyang Pisikal",
      "Heograpiyang Pantao",
      "Kahalagahan ng Katangiang Heograpikal sa Pag-unlad ng Bansa"
    ],
    "Quarter 2": [
      "Mga Pinagkukunang-Yaman ng Bansa",
      "Likas na Yaman",
      "Yamang Lupa",
      "Yamang Tubig",
      "Yamang Gubat",
      "Enerhiyang Mineral",
      "Yamang Tao",
      "Gawaing Pangkabuhayan ng Bansa",
      "Mga Hamon at Pagtugon sa mga Gawaing Pangkabuhayan ng Bansa",
      "Pangangalaga sa mga Pinagkukunang-Yaman ng Bansa",
      "Mga Hamon sa Paggamit ng Likas-kayang Pag-unlad"
    ],
    "Quarter 3": [
      "Elemento ng Pagkabansa",
      "Tao, Teritoryo, Pamahalaan, at Soberanya",
      "Ang Pambansang Pamahalaan",
      "Unitary Presidential System",
      "Separation of Powers",
      "Serbisyo ng Pamahalaan",
      "Pambansang Badyet ng Pilipinas",
      "Serbisyong Panlipunan",
      "Edukasyon, Kultura, at Pagpapaunlad ng Manpower",
      "Panlipunang Kaligtasan, Kagalingan at Empleyo",
      "Kalusugan",
      "Serbisyong Pang-ekonomiya",
      "Komunikasyon, mga Kalsada, at iba pang Transportasyon",
      "Agrikultura, Repormang Pansakahan, at Likas na Yaman at Kapaligiran",
      "Pagpapaunlad ng mga Yamang Tubig at Pagkontrol sa Baha",
      "Pangkalahatang Serbisyong Publiko",
      "Kaayusang Publiko at Kaligtasan",
      "Pangkalahatang Administrasyon"
    ],
    "Quarter 4": [
      "Mga Sagisag ng Pagkakakilanlang Pilipino",
      "Pagkamamamayan",
      "Karapatan at Tungkulin ng Mamamayang Pilipino",
      "Kahulugan at Uri ng Karapatan",
      "Karapatang Sibil",
      "Karapatang Politikal",
      "Karapatang Panlipunan at Pangkabuhayan",
      "Mga Kaakibat na Tungkulin",
      "Kagalingang Pansibiko"
    ]
  },
  "English": {
    "all": [
      "Nouns",
      "Common and Proper Nouns",
      "Plural Nouns",
      "Sentences and Non-Sentences",
      "Simple Sentences",
      "Declarative Sentences",
      "Kinds of Sentences",
      "Punctuation Marks",
      "CVC Words",
      "Short Vowel Words",
      "Rhyming Words",
      "Reading Comprehension",
      "Character, Setting, and Plot",
      "Sequencing Events",
      "Cause and Effect",
      "Drawing Conclusions",
      "Making Predictions"
    ]
  },
  "Filipino": {
    "all": [
      "Pangngalan",
      "Uri ng Pangngalan",
      "Panghalip Panao",
      "Pandiwa",
      "Pang-uri",
      "Pagbasa at Pag-unawa sa Kuwento",
      "Tauhan, Tagpuan, at Banghay",
      "Pagsusunod-sunod ng Pangyayari",
      "Sanhi at Bunga",
      "Paggamit ng Malaki at Maliit na Titik",
      "Mga Bantas",
      "Magkasingkahulugan at Magkasalungat na Salita",
      "Pagbuo ng Pangungusap",
      "Diptonggo at Klaster"
    ]
  },
  "GMRC / Values": {
    "all": [
      "Paggalang sa Sarili",
      "Paggalang sa Kapwa at Nakatatanda",
      "Katapatan",
      "Pagiging Responsable",
      "Pagmamahal sa Pamilya",
      "Pakikipagkaibigan",
      "Disiplina sa Sarili",
      "Pagtulong sa Kapwa",
      "Pagpapahalaga sa Kalikasan",
      "Kabutihang Asal sa Paaralan",
      "Pagiging Matiyaga",
      "Pasasalamat"
    ]
  },
  "MAPEH": {
    "all": [
      "Music: Rhythm and Beat",
      "Music: Notes and Rests",
      "Music: Time Signature",
      "Arts: Lines and Shapes",
      "Arts: Primary and Secondary Colors",
      "Arts: Elements of Art",
      "PE: Locomotor Movements",
      "PE: Non-Locomotor Movements",
      "PE: Mga Larong Pinoy",
      "Health: Wastong Nutrisyon",
      "Health: Kalinisan ng Katawan",
      "Health: Kaligtasan sa Tahanan"
    ]
  },
  "EPP": {
    "all": [
      "Kahalagahan ng Computer at Computing Devices",
      "Monitor, Keyboard, CPU, Mouse at Iba pang Bahagi ng Computer",
      "Booting, Shutting Down, at Keyboarding Techniques",
      "Wastong Posisyon at Layo sa Paggamit ng Computer",
      "Digital Health and Wellness",
      "Online Security and Safety",
      "Phishing, Password, at Personal Information Protection",
      "Word Processing Software - User Interface",
      "Page Setup at Font Formatting",
      "Text Alignment at Saving ng Document"
    ]
  }
}